easymigration/__init__.py
easymigration/batch_processing.py
easymigration/config.py
easymigration/example-easy-migration-tools.yml
easymigration/pids_handling.py
easymigration/scripts/__init__.py
easymigration/scripts/list_bagstore_files.py
easymigration/scripts/update_thematische_collecties.py
easy_migration_tools-0.8.0.dist-info/entry_points.txt
easy_migration_tools-0.8.0.dist-info/WHEEL
easy_migration_tools-0.8.0.dist-info/METADATA
easy_migration_tools-0.8.0.dist-info/RECORD
